{"id": 70, "name": "Ethiopia", "iso3": "ETH", "iso2": "ET", "phone_code": "251", "capital": "Addis Ababa", "currency": "ETB", "states": [{"id": 11, "name": "Addis Ababa", "state_code": "AA", "cities": [{"name": "Addis Ababa", "state": "Addis Ababa"}]}, {"id": 6, "name": "Afar Region", "state_code": "AF", "cities": [{"name": "Administrative Zone 2", "state": "Afar Region"}, {"name": "Administrative Zone 3", "state": "Afar Region"}, {"name": "Asaita", "state": "Afar Region"}, {"name": "\u0100wash", "state": "Afar Region"}, {"name": "Dubti", "state": "Afar Region"}, {"name": "Gewan\u0113", "state": "Afar Region"}, {"name": "Semera", "state": "Afar Region"}]}, {"id": 3, "name": "Amhara Region", "state_code": "AM", "cities": [{"name": "Abomsa", "state": "Amhara Region"}, {"name": "Addiet Canna", "state": "Amhara Region"}, {"name": "\u0100d\u012bs Zemen", "state": "Amhara Region"}, {"name": "Bahir Dar", "state": "Amhara Region"}, {"name": "Bat\u012b", "state": "Amhara Region"}, {"name": "Bichena", "state": "Amhara Region"}, {"name": "Bur\u0113", "state": "Amhara Region"}, {"name": "Dabat", "state": "Amhara Region"}, {"name": "Debark\u2019", "state": "Amhara Region"}, {"name": "Debre Birhan", "state": "Amhara Region"}, {"name": "Debre Mark\u2019os", "state": "Amhara Region"}, {"name": "Debre S\u012bna", "state": "Amhara Region"}, {"name": "Debre Tabor", "state": "Amhara Region"}, {"name": "Debre Werk\u2019", "state": "Amhara Region"}, {"name": "Dejen", "state": "Amhara Region"}, {"name": "Des\u0113", "state": "Amhara Region"}, {"name": "Finote Selam", "state": "Amhara Region"}, {"name": "Gondar", "state": "Amhara Region"}, {"name": "Kemis\u0113", "state": "Amhara Region"}, {"name": "Kombolcha", "state": "Amhara Region"}, {"name": "Lal\u012bbela", "state": "Amhara Region"}, {"name": "North Shewa Zone", "state": "Amhara Region"}, {"name": "North Wollo Zone", "state": "Amhara Region"}, {"name": "Rob\u012bt", "state": "Amhara Region"}, {"name": "South Gondar Zone", "state": "Amhara Region"}, {"name": "South Wollo Zone", "state": "Amhara Region"}, {"name": "Wag Hemra Zone", "state": "Amhara Region"}, {"name": "Were \u012alu", "state": "Amhara Region"}, {"name": "Werota", "state": "Amhara Region"}]}, {"id": 9, "name": "Benishangul-Gumuz Region", "state_code": "BE", "cities": [{"name": "\u0100sosa", "state": "Benishangul-Gumuz Region"}, {"name": "Asosa", "state": "Benishangul-Gumuz Region"}, {"name": "Metekel", "state": "Benishangul-Gumuz Region"}]}, {"id": 8, "name": "Dire Dawa", "state_code": "DD", "cities": [{"name": "Dire Dawa", "state": "Dire Dawa"}]}, {"id": 10, "name": "Gambela Region", "state_code": "GA", "cities": [{"name": "Administrative Zone 1", "state": "Gambela Region"}, {"name": "Gamb\u0113la", "state": "Gambela Region"}]}, {"id": 7, "name": "Harari Region", "state_code": "HA", "cities": [{"name": "Harar", "state": "Harari Region"}]}, {"id": 5, "name": "Oromia Region", "state_code": "OR", "cities": [{"name": "\u0100d\u012bs \u2018Alem", "state": "Oromia Region"}, {"name": "\u0100garo", "state": "Oromia Region"}, {"name": "Arsi Zone", "state": "Oromia Region"}, {"name": "\u0100sasa", "state": "Oromia Region"}, {"name": "\u0100sbe Tefer\u012b", "state": "Oromia Region"}, {"name": "Bedel\u0113", "state": "Oromia Region"}, {"name": "Bed\u0113sa", "state": "Oromia Region"}, {"name": "Bishoftu", "state": "Oromia Region"}, {"name": "Deder", "state": "Oromia Region"}, {"name": "Demb\u012b Dolo", "state": "Oromia Region"}, {"name": "Dodola", "state": "Oromia Region"}, {"name": "East Harerghe Zone", "state": "Oromia Region"}, {"name": "East Shewa Zone", "state": "Oromia Region"}, {"name": "East Wellega Zone", "state": "Oromia Region"}, {"name": "Fich\u0113", "state": "Oromia Region"}, {"name": "Gebre Guracha", "state": "Oromia Region"}, {"name": "G\u0113do", "state": "Oromia Region"}, {"name": "Gelemso", "state": "Oromia Region"}, {"name": "Genet", "state": "Oromia Region"}, {"name": "Gimbi", "state": "Oromia Region"}, {"name": "Ginir", "state": "Oromia Region"}, {"name": "Goba", "state": "Oromia Region"}, {"name": "Gor\u0113", "state": "Oromia Region"}, {"name": "Guji Zone", "state": "Oromia Region"}, {"name": "H\u0101gere Hiywet", "state": "Oromia Region"}, {"name": "Hagere Maryam", "state": "Oromia Region"}, {"name": "H\u012brna", "state": "Oromia Region"}, {"name": "Huruta", "state": "Oromia Region"}, {"name": "Illubabor Zone", "state": "Oromia Region"}, {"name": "Jimma", "state": "Oromia Region"}, {"name": "Jimma Zone", "state": "Oromia Region"}, {"name": "Kibre Mengist", "state": "Oromia Region"}, {"name": "Kofel\u0113", "state": "Oromia Region"}, {"name": "M\u0113ga", "state": "Oromia Region"}, {"name": "Mend\u012b", "state": "Oromia Region"}, {"name": "Metah\u0101ra", "state": "Oromia Region"}, {"name": "Metu", "state": "Oromia Region"}, {"name": "Mojo", "state": "Oromia Region"}, {"name": "Nazr\u0113t", "state": "Oromia Region"}, {"name": "Nejo", "state": "Oromia Region"}, {"name": "North Shewa Zone", "state": "Oromia Region"}, {"name": "Sebeta", "state": "Oromia Region"}, {"name": "Sendafa", "state": "Oromia Region"}, {"name": "Shakiso", "state": "Oromia Region"}, {"name": "Shambu", "state": "Oromia Region"}, {"name": "Shashemen\u0113", "state": "Oromia Region"}, {"name": "Sirre", "state": "Oromia Region"}, {"name": "Tulu Bolo", "state": "Oromia Region"}, {"name": "Waliso", "state": "Oromia Region"}, {"name": "Wenj\u012b", "state": "Oromia Region"}, {"name": "West Harerghe Zone", "state": "Oromia Region"}, {"name": "West Wellega Zone", "state": "Oromia Region"}, {"name": "Yab\u0113lo", "state": "Oromia Region"}, {"name": "Ziway", "state": "Oromia Region"}]}, {"id": 2, "name": "Somali Region", "state_code": "SO", "cities": [{"name": "Afder Zone", "state": "Somali Region"}, {"name": "Degehabur Zone", "state": "Somali Region"}, {"name": "Gode Zone", "state": "Somali Region"}, {"name": "Jijiga", "state": "Somali Region"}, {"name": "Liben zone", "state": "Somali Region"}, {"name": "Shinile Zone", "state": "Somali Region"}]}, {"id": 1, "name": "Southern Nations, Nationalities, and Peoples' Region", "state_code": "SN", "cities": [{"name": "Alaba Special Wereda", "state": "Southern Nations, Nationalities, and Peoples' Region"}, {"name": "Arba Minch", "state": "Southern Nations, Nationalities, and Peoples' Region"}, {"name": "\u0100reka", "state": "Southern Nations, Nationalities, and Peoples' Region"}, {"name": "Bako", "state": "Southern Nations, Nationalities, and Peoples' Region"}, {"name": "Bench Maji Zone", "state": "Southern Nations, Nationalities, and Peoples' Region"}, {"name": "Bod\u012bt\u012b", "state": "Southern Nations, Nationalities, and Peoples' Region"}, {"name": "Bonga", "state": "Southern Nations, Nationalities, and Peoples' Region"}, {"name": "Butaj\u012bra", "state": "Southern Nations, Nationalities, and Peoples' Region"}, {"name": "D\u012bla", "state": "Southern Nations, Nationalities, and Peoples' Region"}, {"name": "Felege Neway", "state": "Southern Nations, Nationalities, and Peoples' Region"}, {"name": "Gedeo Zone", "state": "Southern Nations, Nationalities, and Peoples' Region"}, {"name": "G\u012bdol\u0113", "state": "Southern Nations, Nationalities, and Peoples' Region"}, {"name": "Guraghe Zone", "state": "Southern Nations, Nationalities, and Peoples' Region"}, {"name": "Hadiya Zone", "state": "Southern Nations, Nationalities, and Peoples' Region"}, {"name": "H\u0101gere Selam", "state": "Southern Nations, Nationalities, and Peoples' Region"}, {"name": "Hawassa", "state": "Southern Nations, Nationalities, and Peoples' Region"}, {"name": "Hosa\u2019ina", "state": "Southern Nations, Nationalities, and Peoples' Region"}, {"name": "Jinka", "state": "Southern Nations, Nationalities, and Peoples' Region"}, {"name": "K\u2019ol\u012bto", "state": "Southern Nations, Nationalities, and Peoples' Region"}, {"name": "Kembata Alaba Tembaro Zone", "state": "Southern Nations, Nationalities, and Peoples' Region"}, {"name": "Konso", "state": "Southern Nations, Nationalities, and Peoples' Region"}, {"name": "Leku", "state": "Southern Nations, Nationalities, and Peoples' Region"}, {"name": "Lobuni", "state": "Southern Nations, Nationalities, and Peoples' Region"}, {"name": "M\u012bzan Tefer\u012b", "state": "Southern Nations, Nationalities, and Peoples' Region"}, {"name": "Sheka Zone", "state": "Southern Nations, Nationalities, and Peoples' Region"}, {"name": "Sidama Zone", "state": "Southern Nations, Nationalities, and Peoples' Region"}, {"name": "Sodo", "state": "Southern Nations, Nationalities, and Peoples' Region"}, {"name": "Tippi", "state": "Southern Nations, Nationalities, and Peoples' Region"}, {"name": "Turmi", "state": "Southern Nations, Nationalities, and Peoples' Region"}, {"name": "Wendo", "state": "Southern Nations, Nationalities, and Peoples' Region"}, {"name": "Wolayita Zone", "state": "Southern Nations, Nationalities, and Peoples' Region"}, {"name": "Yem", "state": "Southern Nations, Nationalities, and Peoples' Region"}, {"name": "Yirga \u2018Alem", "state": "Southern Nations, Nationalities, and Peoples' Region"}]}, {"id": 4, "name": "Tigray Region", "state_code": "TI", "cities": [{"name": "\u0100d\u012bgrat", "state": "Tigray Region"}, {"name": "Axum", "state": "Tigray Region"}, {"name": "Inda Silas\u0113", "state": "Tigray Region"}, {"name": "Korem", "state": "Tigray Region"}, {"name": "Maych\u2019ew", "state": "Tigray Region"}, {"name": "Mek'ele", "state": "Tigray Region"}, {"name": "Southeastern Tigray Zone", "state": "Tigray Region"}, {"name": "Southern Tigray Zone", "state": "Tigray Region"}]}]}