{"id": 183, "name": "Rwanda", "iso3": "RWA", "iso2": "RW", "phone_code": "250", "capital": "Kigali", "currency": "RWF", "states": [{"id": 261, "name": "Eastern Province", "state_code": "02", "cities": [{"name": "Kibungo", "state": "Eastern Province"}, {"name": "Rwamagana", "state": "Eastern Province"}]}, {"id": 262, "name": "Kigali district", "state_code": "01", "cities": [{"name": "Kigali", "state": "Kigali district"}]}, {"id": 263, "name": "Northern Province", "state_code": "03", "cities": [{"name": "Byumba", "state": "Northern Province"}, {"name": "Musanze", "state": "Northern Province"}]}, {"id": 259, "name": "Southern Province", "state_code": "05", "cities": [{"name": "Butare", "state": "Southern Province"}, {"name": "Eglise Catholique, Centrale GIKO", "state": "Southern Province"}, {"name": "Gitarama", "state": "Southern Province"}, {"name": "Nzega", "state": "Southern Province"}]}, {"id": 260, "name": "Western Province", "state_code": "04", "cities": [{"name": "Cyangugu", "state": "Western Province"}, {"name": "Gisenyi", "state": "Western Province"}, {"name": "Kibuye", "state": "Western Province"}]}]}