{"id": 217, "name": "Tajikistan", "iso3": "TJK", "iso2": "TJ", "phone_code": "992", "capital": "Dushanbe", "currency": "TJS", "states": [{"id": 3397, "name": "districts of Republican Subordination", "state_code": "RA", "cities": [{"name": "Darband", "state": "districts of Republican Subordination"}, {"name": "Hisor", "state": "districts of Republican Subordination"}, {"name": "Karakenja", "state": "districts of Republican Subordination"}, {"name": "Khodzha-Maston", "state": "districts of Republican Subordination"}, {"name": "Novobod", "state": "districts of Republican Subordination"}, {"name": "Obigarm", "state": "districts of Republican Subordination"}, {"name": "Rasht", "state": "districts of Republican Subordination"}, {"name": "Roghun", "state": "districts of Republican Subordination"}, {"name": "Shahrinav", "state": "districts of Republican Subordination"}, {"name": "Tagob", "state": "districts of Republican Subordination"}, {"name": "Tursunzoda", "state": "districts of Republican Subordination"}, {"name": "Vahdat", "state": "districts of Republican Subordination"}, {"name": "Vahdat District", "state": "districts of Republican Subordination"}, {"name": "Varzob", "state": "districts of Republican Subordination"}, {"name": "Varzob District", "state": "districts of Republican Subordination"}]}, {"id": 3399, "name": "Gorno-Badakhshan Autonomous Province", "state_code": "GB", "cities": [{"name": "Ishqoshim", "state": "Gorno-Badakhshan Autonomous Province"}, {"name": "Khorugh", "state": "Gorno-Badakhshan Autonomous Province"}, {"name": "Murghob", "state": "Gorno-Badakhshan Autonomous Province"}, {"name": "Nohiyai Shughnon", "state": "Gorno-Badakhshan Autonomous Province"}]}, {"id": 3398, "name": "Khatlon Province", "state_code": "KT", "cities": [{"name": "Abdurahmoni Jom\u00ed", "state": "Khatlon Province"}, {"name": "Boshchorbogh", "state": "Khatlon Province"}, {"name": "B\u016dstonqal\u2019a", "state": "Khatlon Province"}, {"name": "Chubek", "state": "Khatlon Province"}, {"name": "Danghara", "state": "Khatlon Province"}, {"name": "D\u016dst\u00ed", "state": "Khatlon Province"}, {"name": "Farkhor", "state": "Khatlon Province"}, {"name": "Gharav\u016dt\u00ed", "state": "Khatlon Province"}, {"name": "Jilik\u016dl", "state": "Khatlon Province"}, {"name": "Kirov", "state": "Khatlon Province"}, {"name": "Kolkhozobod", "state": "Khatlon Province"}, {"name": "K\u016dlob", "state": "Khatlon Province"}, {"name": "Moskovskiy", "state": "Khatlon Province"}, {"name": "M\u016d\u2019minobod", "state": "Khatlon Province"}, {"name": "Nohiyai Kolkhozobod", "state": "Khatlon Province"}, {"name": "Nohiyai Panj", "state": "Khatlon Province"}, {"name": "Nohiyai Vakhsh", "state": "Khatlon Province"}, {"name": "Norak", "state": "Khatlon Province"}, {"name": "Orzu", "state": "Khatlon Province"}, {"name": "Panj", "state": "Khatlon Province"}, {"name": "Q\u016drghonteppa", "state": "Khatlon Province"}, {"name": "Shahritus", "state": "Khatlon Province"}, {"name": "Sovet", "state": "Khatlon Province"}, {"name": "Tartiki", "state": "Khatlon Province"}, {"name": "Vakhsh", "state": "Khatlon Province"}, {"name": "Vose\u2019", "state": "Khatlon Province"}, {"name": "Yovon", "state": "Khatlon Province"}]}, {"id": 3400, "name": "Sughd Province", "state_code": "SU", "cities": [{"name": "Adrasmon", "state": "Sughd Province"}, {"name": "Ayn\u00ed", "state": "Sughd Province"}, {"name": "B\u016dston", "state": "Sughd Province"}, {"name": "Chkalov", "state": "Sughd Province"}, {"name": "Ghafurov", "state": "Sughd Province"}, {"name": "Isfara", "state": "Sughd Province"}, {"name": "Istaravshan", "state": "Sughd Province"}, {"name": "Kh\u016djand", "state": "Sughd Province"}, {"name": "Kim", "state": "Sughd Province"}, {"name": "Konibodom", "state": "Sughd Province"}, {"name": "Konsoy", "state": "Sughd Province"}, {"name": "Neftobod", "state": "Sughd Province"}, {"name": "Nohiyai Konibodom", "state": "Sughd Province"}, {"name": "Nov", "state": "Sughd Province"}, {"name": "Oltintopkan", "state": "Sughd Province"}, {"name": "Pakhtakoron", "state": "Sughd Province"}, {"name": "Palos", "state": "Sughd Province"}, {"name": "Panjakent", "state": "Sughd Province"}, {"name": "Proletar", "state": "Sughd Province"}, {"name": "Quruqsoy", "state": "Sughd Province"}, {"name": "Shaydon", "state": "Sughd Province"}, {"name": "Sh\u016drob", "state": "Sughd Province"}, {"name": "Taboshar", "state": "Sughd Province"}, {"name": "Vorukh", "state": "Sughd Province"}]}]}